easyfred/__init__.py
easyfred/fred.py
easyfred-0.0.1.dist-info/LICENSE
easyfred-0.0.1.dist-info/METADATA
easyfred-0.0.1.dist-info/WHEEL
easyfred-0.0.1.dist-info/top_level.txt
easyfred-0.0.1.dist-info/RECORD
