Metadata-Version: 2.1
Name: easyfred
Version: 0.0.1
Summary: Easy to use Fred API with Python.
Home-page: UNKNOWN
Author: Guillermo Vizcaíno Román
Author-email: <guillevzn@gmail.com>
License: UNKNOWN
Keywords: python,fred,database,API
Platform: UNKNOWN
Classifier: Development Status :: 1 - Planning
Classifier: Intended Audience :: Developers
Classifier: Programming Language :: Python :: 3
Classifier: Operating System :: Unix
Classifier: Operating System :: MacOS :: MacOS X
Classifier: Operating System :: Microsoft :: Windows
Requires-Dist: pandas
